[{"src":"https://img1.doubanio.com/view/subject/s/public/s1070959.jpg","href":"https://book.douban.com/subject/1007305/","title":"红楼梦","subtitle":"","rating":"9.6","pub":"\n        \n  \n  [清] 曹雪芹 著、高鹗 续 / 人民文学出版社 / 1996-12 / 59.70元\n\n      ","pl":"\n        (303763人评价)\n    ","abstract":"《红楼梦》是一部百科全书式的长篇小说。以宝黛爱情悲剧为主线，以四大家族的荣辱兴衰为背景，描绘出18世纪中国封建社会的方方面面，以及封建专制下新兴资本主义民主... ","buylinks":"https://book.douban.com/subject/1007305/buylinks","price":"\n        纸质版 59.10元\n      "},{"src":"https://img2.doubanio.com/view/subject/s/public/s1076932.jpg","href":"https://book.douban.com/subject/1019568/","title":"三国演义（全二册）","subtitle":"","rating":"9.3","pub":"\n        \n  \n  [明] 罗贯中 / 人民文学出版社 / 1998-05 / 39.50元\n\n      ","pl":"\n        (127558人评价)\n    ","abstract":"《三国演义》又名《三国志演义》、《三国志通俗演义》，是我国小说史上最著名最杰出的长篇章回体历史小说。 《三国演义》的作者是元末明初人罗贯中，由毛纶，毛宗岗父... ","price":"","buyhref":"https://book.douban.com/subject/1019568/?channel=subject_list&platform=web"},{"src":"https://img9.doubanio.com/view/subject/s/public/s2280094.jpg","href":"https://book.douban.com/subject/1088581/","title":"浮生六记","subtitle":"","rating":"8.8","pub":"\n        \n  \n  （清）沈复 / 人民文学出版社 / 1999-1 / 5.70元\n\n      ","pl":"\n        (48546人评价)\n    ","abstract":"这是一部自传体文学的作品，原书六卷，已逸其二，现仅存四卷（有所谓“足本”者，后二记系伪作。书中记叙了作者夫妇间平凡的家居生活，坎坷际遇，和各地浪游闻见。文辞... ","buylinks":"https://book.douban.com/subject/1088581/buylinks","price":"\n        纸质版 5.70元\n      "},{"src":"https://img9.doubanio.com/view/subject/s/public/s1627374.jpg","href":"https://book.douban.com/subject/1029553/","title":"西游记（全二册）","subtitle":"","rating":"8.9","pub":"\n        \n  \n  吴承恩 / 黄肃秋 注释 / 人民文学出版社 / 2004-8 / 47.20元\n\n      ","pl":"\n        (61617人评价)\n    ","abstract":"《西游记》主要描写的是孙悟空保唐僧西天取经，历经九九八十一难的故事。唐僧取经是历史上一件真实的事。大约距今一千三百多年前，即唐太宗贞观元年（627），年仅2... ","buylinks":"https://book.douban.com/subject/1029553/buylinks","price":"\n        纸质版 46.70元\n      "},{"src":"https://img1.doubanio.com/view/subject/s/public/s29703857.jpg","href":"https://book.douban.com/subject/30137806/","title":"红楼梦","subtitle":"","rating":"9.8","pub":"\n        \n  \n  曹雪芹 / 人民文学出版社 / 2018-1-1 / CNY 260.00\n\n      ","pl":"\n        (4142人评价)\n    ","abstract":"《红楼梦》，中国古代古代四大名著之一，也是中国古代小说的巅峰之作。全书以荣国府的日常生活为中心，以宝玉、黛玉、宝钗的爱情婚姻悲剧及大观园中点滴琐事为主线，以... ","buylinks":"https://book.douban.com/subject/30137806/buylinks","price":"\n        纸质版 257.40元\n      "},{"src":"https://img2.doubanio.com/view/subject/s/public/s1979223.jpg","href":"https://book.douban.com/subject/1883245/","title":"诗经","subtitle":"","rating":"9.4","pub":"\n        \n  \n  孔丘 编订 / 北京出版社 / 2006-7 / 19.90元\n\n      ","pl":"\n        (18734人评价)\n    ","abstract":"这本《诗经》收录全部305篇，每篇诗歌都配有相应的解释及译文，使读者更容易理解。 ","buylinks":"https://book.douban.com/subject/1883245/buylinks","price":"\n        纸质版 25.30元起\n      "},{"src":"https://img1.doubanio.com/view/subject/s/public/s1436519.jpg","href":"https://book.douban.com/subject/1008357/","title":"水浒传（全二册）","subtitle":"","rating":"8.6","pub":"\n        \n  \n  [明] 施耐庵、罗贯中 / 人民文学出版社 / 1997-1 / 50.60元\n\n      ","pl":"\n        (59880人评价)\n    ","abstract":"《水浒传》是我国第一部以农民起义为题材的长篇章回小说，是我国文学史上一座巍然屹立的丰碑，也是世界文学宝库中一颗光彩夺目的明珠。数百年来，它一直深受我国人民的... ","price":"","buyhref":"https://book.douban.com/subject/1008357/?channel=subject_list&platform=web"},{"src":"https://img3.doubanio.com/view/subject/s/public/s33595450.jpg","href":"https://book.douban.com/subject/34995672/","title":"中国妖怪故事（全集）","subtitle":" : 中国妖怪大百科全书 ","rating":"8.4","pub":"\n        \n  \n  张云 / 低音 • 北京联合出版公司 / 2020-6 / 128.00元\n\n      ","pl":"\n        (400人评价)\n    ","abstract":"★★★\n中国妖怪大百科全书，辑录历代典籍文献近300部，整理1080种妖怪及其故事，还原根植于中国的日本妖怪本来面貌。\n上海交通大学资深教授、中国社会科学院... ","price":"","buyhref":"https://book.douban.com/subject/34995672/?channel=subject_list&platform=web"},{"src":"https://img1.doubanio.com/view/subject/s/public/s1008848.jpg","href":"https://book.douban.com/subject/1013267/","title":"唐诗三百首","subtitle":"","rating":"9.4","pub":"\n        \n  \n  蘅塘退士、陈婉俊 / 中华书局 / 1998-1-1 / 0.65\n\n      ","pl":"\n        (15827人评价)\n    ","abstract":"《唐诗三百首》的旧注本亦有许多种，其中以陈婉俊的补注本简明精当，流行最广。她的注解除简介作者生平外，比较注重语词名物的诠释，博引旁征，字梳句栉，对今天的读者... ","buylinks":"https://book.douban.com/subject/1013267/buylinks","price":"\n        纸质版 3.00元起\n      "},{"src":"https://img9.doubanio.com/view/subject/s/public/s5804746.jpg","href":"https://book.douban.com/subject/1964774/","title":"论语","subtitle":"","rating":"9.1","pub":"\n        \n  \n  中华书局 / 2006-12 / 9.80元\n\n      ","pl":"\n        (14090人评价)\n    ","abstract":"《论语》是一部语录体思想散文集。早在春秋后期孔子设坛讲学时期，其主体内容就已初始创成；孔子去世以后，他的辫子和再传弟子代代传授他的言论，并逐渐将这些口头记诵... ","buylinks":"https://book.douban.com/subject/1964774/buylinks","price":"\n        纸质版 7.10元\n      "},{"src":"https://img1.doubanio.com/view/subject/s/public/s26303678.jpg","href":"https://book.douban.com/subject/1916451/","title":"金瓶梅","subtitle":"","rating":"9.2","pub":"\n        \n  \n  笑笑生【著】、董玉振【校】 / 新加坡南洋出版社 / 2009-11-1 / 466\n\n      ","pl":"\n        (3032人评价)\n    ","abstract":"这套《金瓶梅》（上、下册，约1240印刷页）是全球第一部简体、双版本、带200原图（其中30多幅春宫图也全部保留）、不做任何删节处理的版本。是目前海内外各种... ","price":""},{"src":"https://img2.doubanio.com/view/subject/s/public/s1325863.jpg","href":"https://book.douban.com/subject/1014561/","title":"古文观止","subtitle":"","rating":"9.1","pub":"\n        \n  \n  吴楚材、吴调侯 / 中华书局 / 1987-1-1 / 21.00元\n\n      ","pl":"\n        (14444人评价)\n    ","abstract":"《古文观止》是清康熙年间吴乘权、吴大职编选的一部古文读本，凡十二卷，收录自先秦至明末的散文二百二十二篇，每篇都有注释和评论。据《左传》襄公二十九年记载，吴公... ","buylinks":"https://book.douban.com/subject/1014561/buylinks","price":"\n        纸质版 26.90元起\n      "},{"src":"https://img3.doubanio.com/view/subject/s/public/s3888781.jpg","href":"https://book.douban.com/subject/3810699/","title":"水浒传","subtitle":" : 水浒传 ","rating":"9.0","pub":"\n        \n  \n  施耐庵、罗贯中 / 中华书局 / 2009-06 / 88.00元\n\n      ","pl":"\n        (4441人评价)\n    ","abstract":"有人说，读《水浒传》不读金圣叹的评语，等于没读过《水浒传》，此言不虚。《水浒传》是一部经过宋、元两代数百年的酝酿、积累而最终完成的长篇历史小说，集合了无数英... ","buylinks":"https://book.douban.com/subject/3810699/buylinks","price":"\n        纸质版 84.50元\n      "},{"src":"https://img3.doubanio.com/view/subject/s/public/s1045431.jpg","href":"https://book.douban.com/subject/1059258/","title":"道德经","subtitle":"","rating":"9.4","pub":"\n        \n  \n  黄元吉 / 陕西人民出版社 / 1996-10 / 4.50元\n\n      ","pl":"\n        (13237人评价)\n    ","abstract":"《道德經》，又稱《道德真經》、《老子》、《五千言》、《老子五千文》，是中國古代先秦諸子分家前的一部著作，為其時諸子所共仰，傳說是春秋時期的老子李耳所撰寫，是... ","buylinks":"https://book.douban.com/subject/1059258/buylinks","price":"\n        纸质版 23.00元起\n      "},{"src":"https://img9.doubanio.com/view/subject/s/public/s28295535.jpg","href":"https://book.douban.com/subject/26610864/","title":"浮生六记","subtitle":"","rating":"8.1","pub":"\n        \n  \n  沈复 / 张佳玮 / 天津人民出版社 / 2015-8 / 32.00元\n\n      ","pl":"\n        (24876人评价)\n    ","abstract":"并不能用有趣、精致、伤感简单概括这本小书。之所以入得经典行列，约是手边有此一册，便真如有一妙友相伴。\n本次出版选开明书店民国本为底本，考以《雁来红丛报》本、... ","price":"","buyhref":"https://book.douban.com/subject/26610864/?channel=subject_list&platform=web"},{"src":"https://img9.doubanio.com/view/subject/s/public/s1075414.jpg","href":"https://book.douban.com/subject/1073708/","title":"牡丹亭","subtitle":"","rating":"9.0","pub":"\n        \n  \n  汤显祖 / 人民文学出版社 / 1963-4-1 / 14.50元\n\n      ","pl":"\n        (10009人评价)\n    ","abstract":"《牡丹亭》是明代大曲家汤显祖的代表作，这时作家的思想\n和艺术都已经成熟。明代话本小说《杜丽娘慕色还魂》为《牡丹亭》提供了基本情节。《牡丹亭》在《惊梦》《寻梦... ","buylinks":"https://book.douban.com/subject/1073708/buylinks","price":"\n        纸质版 11.20元\n      "},{"src":"https://img3.doubanio.com/view/subject/s/public/s33320950.jpg","href":"https://book.douban.com/subject/34463395/","title":"诗人十四个","subtitle":"","rating":"8.8","pub":"\n        \n  \n  黄晓丹 / 北京联合出版公司 / 2019-7 / 52.00元\n\n      ","pl":"\n        (1180人评价)\n    ","abstract":"十四位古代诗人和一个现代闯入者\n一场始于1600年前的诗歌沙龙\n·\n七堂围绕“春天”意象与“青春”经验的文学课，\n以现代心理学解读古代诗人，\n诗与心灵自由飞... ","price":"","buyhref":"https://book.douban.com/subject/34463395/?channel=subject_list&platform=web"},{"src":"https://img9.doubanio.com/view/subject/s/public/s1909396.jpg","href":"https://book.douban.com/subject/1042053/","title":"儒林外史","subtitle":"","rating":"8.3","pub":"\n        \n  \n  吴敬梓 / 人民文学出版社 / 2002-1-1 / 20.00\n\n      ","pl":"\n        (7307人评价)\n    ","abstract":"吴敬梓的《儒林外史》是中国小说史上少有的几部出类拔萃的巨制之一，是唯一一部真正意义上的讽刺小说。\n    吴敬梓在创作此书时，以对待功名富贵和文行出处的态度... ","buylinks":"https://book.douban.com/subject/1042053/buylinks","price":"\n        纸质版 5.20元起\n      "},{"src":"https://img1.doubanio.com/view/subject/s/public/s4550508.jpg","href":"https://book.douban.com/subject/4903692/","title":"东京梦华录","subtitle":"","rating":"9.1","pub":"\n        \n  \n  孟元老 / 中州古籍出版社 / 2010-6-1 / 20.00元\n\n      ","pl":"\n        (2416人评价)\n    ","abstract":"《东京梦华录》多记崇宁以后所见，时方以逸豫临下，故若彩山灯火，水殿争标，宝津男女诸戏，走马角射，及天宁节女队归骑，年少争迎，虽事隔前载，犹令人想见其盛。至如... ","buylinks":"https://book.douban.com/subject/4903692/buylinks","price":"\n        纸质版 17.60元\n      "},{"src":"https://img2.doubanio.com/view/subject/s/public/s9125702.jpg","href":"https://book.douban.com/subject/1061803/","title":"西游记","subtitle":"","rating":"9.2","pub":"\n        \n  \n  吴承恩 / 岳麓书社 / 1994-04 / 15.00\n\n      ","pl":"\n        (8659人评价)\n    ","abstract":"《西游记》的艺术虚构正是建立在传统艺术经验和这种社会的宗教性观念和风习的基础之上的，但它又以作者融会了传统艺术经验所形成的艺术的独创性批判了社会的宗教性观念... ","buylinks":"https://book.douban.com/subject/1061803/buylinks","price":"\n        纸质版 18.10元起\n      "}]