[{"src":"https://img1.doubanio.com/view/subject/s/public/s23632058.jpg","href":"https://book.douban.com/subject/1255625/","title":"天龙八部","subtitle":"","rating":"9.1","pub":"\n        \n  \n  金庸 / 生活.读书.新知三联书店 / 1994-5 / 96.0\n\n      ","pl":"\n        (105910人评价)\n    ","abstract":"天龙八部乃金笔下的一部长篇小说，与《射雕》，《神雕》等 几部长篇小说一起被称为可读性最高的金庸小说。《天龙》的故事情节曲折，内容丰富，也曾多次被改编为电视作... ","buylinks":"https://book.douban.com/subject/1255625/buylinks","price":"\n        纸质版 148.80元起\n      "},{"src":"https://img9.doubanio.com/view/subject/s/public/s2157335.jpg","href":"https://book.douban.com/subject/1002299/","title":"笑傲江湖（全四册）","subtitle":"","rating":"9.0","pub":"\n        \n  \n  金庸 / 生活·读书·新知三联书店 / 1994-5 / 76.80元\n\n      ","pl":"\n        (90958人评价)\n    ","abstract":"《笑傲江湖》是金庸1967年写的一部武侠小说，属于金庸的后期作品。 ","buylinks":"https://book.douban.com/subject/1002299/buylinks","price":"\n        纸质版 122.90元起\n      "},{"src":"https://img9.doubanio.com/view/subject/s/public/s2157336.jpg","href":"https://book.douban.com/subject/1044547/","title":"射雕英雄传（全四册）","subtitle":"","rating":"9.0","pub":"\n        \n  \n  金庸 / 生活·读书·新知三联书店 / 1999-04 / 47.00元\n\n      ","pl":"\n        (66867人评价)\n    ","abstract":"《射雕英雄传》是金庸的代表作之一，作于一九五七年到一九五九年，在《香港商报》连载。《射雕》中的人物个性单纯，郭靖诚朴厚重、黄蓉机智狡狯，读者容易印象深刻。这... ","buylinks":"https://book.douban.com/subject/1044547/buylinks","price":"\n        纸质版 72.80元起\n      "},{"src":"https://img9.doubanio.com/view/subject/s/public/s26018916.jpg","href":"https://book.douban.com/subject/1255624/","title":"神雕侠侣","subtitle":"","rating":"8.9","pub":"\n        \n  \n  金庸 / 有1996年11月北平第4次印本 / 生活·读书·新知三联书店 / 1994-5 / 76.80元\n\n      ","pl":"\n        (82369人评价)\n    ","abstract":"《神雕侠侣》是金庸作品集之一。其主人公杨过自然而然地走上了非正统的人生道路，入了“道流”。其特点是“至情至性，实现自我”，即把个人的利益、情感、个性及人格尊... ","buylinks":"https://book.douban.com/subject/1255624/buylinks","price":"\n        纸质版 89.10元起\n      "},{"src":"https://img3.doubanio.com/view/subject/s/public/s3134040.jpg","href":"https://book.douban.com/subject/1212893/","title":"鹿鼎记（全五册）","subtitle":"","rating":"8.8","pub":"\n        \n  \n  金庸 / 广州出版社 花城出版社 / 2008-3 / 108.00元\n\n      ","pl":"\n        (46637人评价)\n    ","abstract":"《鹿鼎记》是金庸创作的最后一部小说，也是他最重要的代表作。\n小说讲的是一个从小在扬州妓院长大的小孩韦小宝，他以不会任何武功之姿态闯江湖各大帮会、周旋皇帝朝臣... ","buylinks":"https://book.douban.com/subject/1212893/buylinks","price":"\n        纸质版 48.00元\n      "},{"src":"https://img1.doubanio.com/view/subject/s/public/s1829709.jpg","href":"https://book.douban.com/subject/1070851/","title":"倚天屠龙记(共四册)","subtitle":"","rating":"8.6","pub":"\n        \n  \n  金庸 / 三联书店 / 1999-04 / 47.00\n\n      ","pl":"\n        (50766人评价)\n    ","abstract":"《倚天屠龙记》，金庸武侠小说，著于1961年，是“射雕三部曲”系列第三部，现收录在《金庸作品集》中。该书以元末群雄纷起、江湖动荡为广阔背景，叙述武当弟子张无... ","buylinks":"https://book.douban.com/subject/1070851/buylinks","price":"\n        纸质版 29.10元起\n      "},{"src":"https://img2.doubanio.com/view/subject/s/public/s2655602.jpg","href":"https://book.douban.com/subject/1793132/","title":"白马啸西风","subtitle":"","rating":"7.6","pub":"\n        \n  \n  金庸 / 海口-南海出版社 / 1993-11\n\n      ","pl":"\n        (20665人评价)\n    ","abstract":"这是篇言情故事，写出了单恋的种种动人之处。 ","buylinks":"https://book.douban.com/subject/1793132/buylinks","price":"\n        纸质版 15.00元起\n      "},{"src":"https://img3.doubanio.com/view/subject/s/public/s7062091.jpg","href":"https://book.douban.com/subject/10466059/","title":"射雕英雄传（全4册）","subtitle":"","rating":"9.1","pub":"\n        \n  \n  金庸 / 广州出版社 / 2013-4 / 96.00元\n\n      ","pl":"\n        (2780人评价)\n    ","abstract":"南宋年间，随丈夫杨铁心流落江南牛家村的包惜弱救了金国王子完颜洪烈，却害得丈夫和义兄郭啸天两家家破人亡。郭啸天的妻子逃到蒙古大漠，生下遗腹子郭靖。傻小子郭靖得... ","buylinks":"https://book.douban.com/subject/10466059/buylinks","price":"\n        纸质版 58.70元\n      "},{"src":"https://img1.doubanio.com/view/subject/s/public/s24555597.jpg","href":"https://book.douban.com/subject/4832584/","title":"笑傲江湖","subtitle":"","rating":"9.3","pub":"\n        \n  \n  金庸 / 广州出版社 / 2011-11 / 98.00元\n\n      ","pl":"\n        (3354人评价)\n    ","abstract":"名门正派的华山派大弟子令狐冲只因心性自由、不受羁勒，喜欢结交左道人士，被逐出师门，遭到正宗门派武林人士的唾弃而流落江湖。令狐冲依然率性而为，只因正义良知自在... ","buylinks":"https://book.douban.com/subject/4832584/buylinks","price":"\n        纸质版 62.20元\n      "},{"src":"https://img2.doubanio.com/view/subject/s/public/s28267663.jpg","href":"https://book.douban.com/subject/1789837/","title":"射雕英雄传","subtitle":"","rating":"9.0","pub":"\n        \n  \n  金庸 / 生活·读书·新知三联书店 / 1994-5 / 76.80元\n\n      ","pl":"\n        (18463人评价)\n    ","abstract":"《射雕英雄传》是金庸的代表作之一，作于一九五七年到一九五九年，在《香港商报》连载。《射雕》中的人物个性单纯，郭靖诚朴厚重、黄蓉机智狡狯，读者容易印象深刻。这... ","buylinks":"https://book.douban.com/subject/1789837/buylinks","price":"\n        纸质版 71.50元起\n      "},{"src":"https://img3.doubanio.com/view/subject/s/public/s7062701.jpg","href":"https://book.douban.com/subject/6969074/","title":"天龙八部","subtitle":"","rating":"9.4","pub":"\n        \n  \n  金庸 / 广州出版社 / 2011-11 / 123.00元\n\n      ","pl":"\n        (3205人评价)\n    ","abstract":"《天龙八部(套装共5册)(旧版)》一书以北宋、辽、西夏、大理并立的历史为宏大背景，将儒释道、琴棋书画等中国传统文化融会贯通其中，书中人物繁多，个性鲜明，情节... ","buylinks":"https://book.douban.com/subject/6969074/buylinks","price":"\n        纸质版 74.70元\n      "},{"src":"https://img1.doubanio.com/view/subject/s/public/s1879839.jpg","href":"https://book.douban.com/subject/1559310/","title":"鹿鼎记","subtitle":"","rating":"9.0","pub":"\n        \n  \n  金庸 / 生活·读书·新知三联书店 / 1994-5 / 96.00元\n\n      ","pl":"\n        (12916人评价)\n    ","abstract":"这是金庸先生最後一部小说，也是登峰造极之作，是金大侠自言最喜欢之大作。          这部小说讲的是一个从小在扬州妓院长大的小孩韦小宝，他不会任何武功，... ","buylinks":"https://book.douban.com/subject/1559310/buylinks","price":"\n        纸质版 160.00元起\n      "},{"src":"https://img9.doubanio.com/view/subject/s/public/s26018914.jpg","href":"https://book.douban.com/subject/1789841/","title":"倚天屠龙记","subtitle":"","rating":"8.7","pub":"\n        \n  \n  金庸 / 生活·读书·新知三联书店 / 1994年5月 / 76.80\n\n      ","pl":"\n        (17672人评价)\n    ","abstract":"《倚天屠龙记》，金庸武侠小说，著于1961年，是“射雕三部曲”系列第三部。该书以元末群雄纷起、江湖动荡为广阔背景，叙述武当弟子张无忌的江湖生涯，表现众武林豪... ","buylinks":"https://book.douban.com/subject/1789841/buylinks","price":"\n        纸质版 0.99元起\n      "},{"src":"https://img9.doubanio.com/view/subject/s/public/s24938374.jpg","href":"https://book.douban.com/subject/1789842/","title":"侠客行","subtitle":"","rating":"7.4","pub":"\n        \n  \n  金庸 / 生活·读书·新知三联书店 / 1994-5 / 38.00元\n\n      ","pl":"\n        (13434人评价)\n    ","abstract":"《侠客行》著于1965年，据说灵感和书名来自李白的诗作“古风五十九首”之《侠客行》。小说叙述的是一个懵懂少年石破天的江湖经历。\n主人公石破天自小没名没姓，和... ","buylinks":"https://book.douban.com/subject/1789842/buylinks","price":"\n        纸质版 58.80元起\n      "},{"src":"https://img3.doubanio.com/view/subject/s/public/s2157330.jpg","href":"https://book.douban.com/subject/1068308/","title":"雪山飞狐","subtitle":"","rating":"7.6","pub":"\n        \n  \n  金庸 / 三联书店 / 1999-04 / 12.00元\n\n      ","pl":"\n        (20304人评价)\n    ","abstract":"本书与金庸另一部小说《飞狐外传》情节相关联，但又各自独立。故事发生在清代乾隆时期的关外。饮马川陶百岁、陶子安父子从雪山中挖出一件宝物，封于铁盒之中。北京平通... ","buylinks":"https://book.douban.com/subject/1068308/buylinks","price":"\n        纸质版 55.70元起\n      "},{"src":"https://img9.doubanio.com/view/subject/s/public/s26011435.jpg","href":"https://book.douban.com/subject/1058956/","title":"碧血剑","subtitle":"","rating":"7.4","pub":"\n        \n  \n  金庸 / 生活.读书.新知三联书店 / 1994-05 / 38.0\n\n      ","pl":"\n        (9239人评价)\n    ","abstract":"《碧血剑》当代著名作家金庸著，著于1956年，是金庸的第二部武侠小说。至今为止，已经过三次修订。现收录在《金庸作品集》中。\n本书讲的是明末抗清将领袁崇焕之子... ","buylinks":"https://book.douban.com/subject/1058956/buylinks","price":"\n        纸质版 27.70元起\n      "},{"src":"https://img1.doubanio.com/view/subject/s/public/s26018268.jpg","href":"https://book.douban.com/subject/1442037/","title":"书剑恩仇录","subtitle":" : 有1996年11月北平第4次印本 ","rating":"7.2","pub":"\n        \n  \n  金庸 / 生活·读书·新知三联书店 / 1994-5 / 38.00\n\n      ","pl":"\n        (9421人评价)\n    ","abstract":"本书是《金庸作品集》之一，也是金庸的第一部小说。书中的内容主要是写红花会英雄试图通过换一个汉族皇帝，乃至通过同一皇帝换一套汉族服装，便以为是抗清大计的完成，... ","buylinks":"https://book.douban.com/subject/1442037/buylinks","price":"\n        纸质版 59.30元起\n      "},{"src":"https://img1.doubanio.com/view/subject/s/public/s7062867.jpg","href":"https://book.douban.com/subject/10466761/","title":"倚天屠龙记","subtitle":"","rating":"8.9","pub":"\n        \n  \n  金庸 / 广州出版社 / 2012-8 / 96.00元\n\n      ","pl":"\n        (2025人评价)\n    ","abstract":"小说以元朝末年为历史背景，叙述了明教教主、武当弟子张无忌率领明教教众和江湖豪杰反抗元朝暴政的故事。不祥的屠龙刀使主人公少年张无忌幼失怙恃，身中玄冥毒掌，历尽... ","buylinks":"https://book.douban.com/subject/10466761/buylinks","price":"\n        纸质版 58.70元\n      "},{"src":"https://img2.doubanio.com/view/subject/s/public/s27084783.jpg","href":"https://book.douban.com/subject/1076045/","title":"连城诀","subtitle":"","rating":"7.7","pub":"\n        \n  \n  金庸 / 三联书店 / 1999-04 / 12.00\n\n      ","pl":"\n        (20176人评价)\n    ","abstract":"本部书初发行是以「素心剑」为名，是金庸先生以小时候一段回忆为主而发展出来的故事，疼爱他的家中长工因为冤狱郁郁一生，心中的委屈至垂死才吐露于他。\n「连城诀」以... ","buylinks":"https://book.douban.com/subject/1076045/buylinks","price":"\n        纸质版 39.10元起\n      "},{"src":"https://img9.doubanio.com/view/subject/s/public/s10520306.jpg","href":"https://book.douban.com/subject/4116115/","title":"神雕侠侣","subtitle":"","rating":"9.0","pub":"\n        \n  \n  金庸 / 廣州出版社 / 2011-11 / 88.元\n\n      ","pl":"\n        (1313人评价)\n    ","abstract":"南宋年间，蒙古大军围攻襄阳城。大侠郭靖带领城内军民殊死抵抗。郭靖义弟杨康的遗腹子杨过投身古墓派 ，并与师父小龙女展开一场为世俗所不容的师徒之恋。欲杀郭靖为父... ","price":""}]