[{"src":"https://img9.doubanio.com/view/subject/s/public/s27653114.jpg","href":"https://book.douban.com/subject/26163553/","title":"投资中最简单的事","subtitle":"","rating":"8.7","pub":"\n        \n  \n  邱国鹭 / 中国人民大学出版社 / 2014-10 / 45.90\n\n      ","pl":"\n        (6602人评价)\n    ","abstract":"[内容简介]\n●投资本身是一件很复杂的事，宏观上涉及国家的政治、经济、历史、军事，中观上涉及行业格局演变、产业技术进步、上下游产业链变迁，微观上涉及企业的发... ","buylinks":"https://book.douban.com/subject/26163553/buylinks","price":"\n        纸质版 34.40元\n      "},{"src":"https://img2.doubanio.com/view/subject/s/public/s6462582.jpg","href":"https://book.douban.com/subject/5243775/","title":"聪明的投资者","subtitle":"","rating":"8.9","pub":"\n        \n  \n  本杰明·格雷厄姆、Benjamin Graham / 王中华、黄一义 / 人民邮电出版社 / 2010-8 / 88.00元\n\n      ","pl":"\n        (5703人评价)\n    ","abstract":"这是一本投资实务领域的世界级和世纪级的经典著作，自从1949年首次出版以来，本书即成为股市上的《圣经》。本修订版在完整保留格雷厄姆原著1973年第4版的基础... ","buylinks":"https://book.douban.com/subject/5243775/buylinks","price":"\n        纸质版 70.40元\n      "},{"src":"https://img2.doubanio.com/view/subject/s/public/s8857282.jpg","href":"https://book.douban.com/subject/6974582/","title":"股票作手回忆录","subtitle":"","rating":"8.8","pub":"\n        \n  \n  杰西·利弗莫尔 / 黄程雅淑，马晓佳 / 中国青年出版社 / 2012-1 / 33.90元\n\n      ","pl":"\n        (2797人评价)\n    ","abstract":"《彼得林奇点评版股票作手回忆录:巴菲特指定股市教科书》充满了利弗莫尔的人生和投资思路。他曾数次大起大落，做多和做空都赚过大钱，一生积攒的经验，后来历代的股神... ","price":"","buyhref":"https://book.douban.com/subject/6974582/?channel=subject_list&platform=web"},{"src":"https://img1.doubanio.com/view/subject/s/public/s27220989.jpg","href":"https://book.douban.com/subject/25829645/","title":"股市进阶之道","subtitle":" : 一个散户的自我修养 ","rating":"8.8","pub":"\n        \n  \n  李杰 / 中国铁道出版社 / 2014-3 / 55\n\n      ","pl":"\n        (1764人评价)\n    ","abstract":"本书是集作者数十年经验为个人投资者而作的一本书，其核心内容分为三大部分，其分别对应着投资之道、价值之源和估值之谜。\n它们正是投资中最为关键和困难的部分、其既... ","price":"","buyhref":"https://book.douban.com/subject/25829645/?channel=subject_list&platform=web"},{"src":"https://img3.doubanio.com/view/subject/s/public/s29962571.jpg","href":"https://book.douban.com/subject/30416923/","title":"价值投资实战手册","subtitle":"","rating":"8.9","pub":"\n        \n  \n  唐朝 / 中国经济出版社 / 2019-1 / 59.80\n\n      ","pl":"\n        (897人评价)\n    ","abstract":"本书是老唐对20多年投资实践中形成的投资体系的回顾与总结，由三大章构成：正确面对股价波动、如何估算内在价值、企业分析案例。\n前两章完整地阐述了老唐个人对投资... ","price":"","buyhref":"https://book.douban.com/subject/30416923/?channel=subject_list&platform=web"},{"src":"https://img2.doubanio.com/view/subject/s/public/s29175222.jpg","href":"https://book.douban.com/subject/26290085/","title":"手把手教你读财报","subtitle":" : 财报是用来排除企业的 ","rating":"8.7","pub":"\n        \n  \n  唐朝 / 中国经济出版社 / 2015-1-1 / 49.00元\n\n      ","pl":"\n        (3273人评价)\n    ","abstract":"本书是一位久经沙场的老股民，在经历了无数次惨烈的投资战役之后，总结过往得失，呕心沥血而作。因为不是会计专业出身，所以没有晦涩的术语、难懂的公式。因为有多年的... ","price":"","buyhref":"https://book.douban.com/subject/26290085/?channel=subject_list&platform=web"},{"src":"https://img3.doubanio.com/view/subject/s/public/s26590200.jpg","href":"https://book.douban.com/subject/24092345/","title":"证券分析","subtitle":" : 第6版（平装上、下） ","rating":"9.1","pub":"\n        \n  \n  [美]本杰明•格雷厄姆（Benjamin Graham）、[美]戴维•多德（David L. Dodd） / 巴曙松、陈剑 / 中国人民大学出版社 / 2013-4 / 129.90元\n\n      ","pl":"\n        (1272人评价)\n    ","abstract":"\t《证券分析》被誉为投资者的圣经，自1934年出版以来，八十年畅销不衰。市场反复证明，《证券分析》是价值投资的经典之作。《证券分析》第6版是1940年版本... ","buylinks":"https://book.douban.com/subject/24092345/buylinks","price":"\n        纸质版 97.40元\n      "},{"src":"https://img2.doubanio.com/view/subject/s/public/s4409283.jpg","href":"https://book.douban.com/subject/4827219/","title":"彼得·林奇的成功投资","subtitle":"","rating":"9.1","pub":"\n        \n  \n  彼得·林奇、约翰·罗瑟查尔德 / 刘建位、徐晓杰 / 机械工业出版社 / 2010-4-1 / 38.00元\n\n      ","pl":"\n        (1946人评价)\n    ","abstract":"彼得.林奇的成功投资（珍藏版），ISBN：9787111302490，作者：（美）林奇，（美）罗瑟查尔德 著，刘建位，徐晓杰 译 ","buylinks":"https://book.douban.com/subject/4827219/buylinks","price":"\n        纸质版 29.00元\n      "},{"src":"https://img2.doubanio.com/view/subject/s/public/s2414322.jpg","href":"https://book.douban.com/subject/1087737/","title":"日本蜡烛图技术","subtitle":" : 古老东方投资术的现代指南 ","rating":"8.9","pub":"\n        \n  \n  （美）史蒂夫.尼森 / 丁圣元 / 地震出版社 / 1998-05-01 / 60.00元\n\n      ","pl":"\n        (4067人评价)\n    ","abstract":"《日本蜡烛图技术:古老东方投资术的现代指南》是对技术分析书面资料的一项激动人心的、价值不菲的充实。它以详实、流畅、精辟易懂的语言，有史以来第一次，将这门古老... ","buylinks":"https://book.douban.com/subject/1087737/buylinks","price":"\n        纸质版 45.00元\n      "},{"src":"https://img9.doubanio.com/view/subject/s/public/s29751634.jpg","href":"https://book.douban.com/subject/30194663/","title":"股市真规则（畅销版）","subtitle":" : 站在巴菲特和晨星公司的肩上投资 ","rating":"9.0","pub":"\n        \n  \n  帕特多尔西 / 中信出版集团 / 2018-4 / 65\n\n      ","pl":"\n        (470人评价)\n    ","abstract":"对于投资一窍不通就盲目入市？\n对于公司的现状和未来并不清晰就跟风买入？\n迷信“小道消息”而不愿意研究公司和行业？\n莫名其妙经常成为“韭菜”被收割？\n对于不愿... ","buylinks":"https://book.douban.com/subject/30194663/buylinks","price":"\n        纸质版 32.50元\n      "},{"src":"https://img3.doubanio.com/view/subject/s/public/s1989131.jpg","href":"https://book.douban.com/subject/1958714/","title":"彼得·林奇的成功投资","subtitle":"","rating":"8.7","pub":"\n        \n  \n  [美] 彼得·林奇、约翰·罗瑟查尔德 / 刘建位、徐晓杰 / 机械工业出版社 / 2007-1 / 38.00元\n\n      ","pl":"\n        (6369人评价)\n    ","abstract":"作者用浅显生动的语言娓娓道出了股票投资的诸多技巧，向广大的中小投资者提供了简单易学的投资分析方法，这些方法是作者多年的经验总结，具有很强的实践性，对于业余投... ","buylinks":"https://book.douban.com/subject/1958714/buylinks","price":"\n        纸质版 34.20元\n      "},{"src":"https://img1.doubanio.com/view/subject/s/public/s26682138.jpg","href":"https://book.douban.com/subject/24325274/","title":"海龟交易法则","subtitle":"","rating":"8.7","pub":"\n        \n  \n  柯蒂斯•费思 / 乔江涛 / 中信出版社 / 2013-5 / 59\n\n      ","pl":"\n        (1615人评价)\n    ","abstract":"在金融界，流传着这样一个著名的故事。1983年，美国期货界的两个挚友——理查德•丹尼斯与威廉•埃克哈特之间就一个问题产生了分歧：伟大的期货交易者究竟是天生的... ","price":"","buyhref":"https://book.douban.com/subject/24325274/?channel=subject_list&platform=web"},{"src":"https://img1.doubanio.com/view/subject/s/public/s4168679.jpg","href":"https://book.douban.com/subject/4244804/","title":"笑傲股市","subtitle":"","rating":"8.4","pub":"\n        \n  \n  （美）欧奈尔 / 宋三江 / 机械工业出版社 / 2010-1-1 / 58.00元\n\n      ","pl":"\n        (1094人评价)\n    ","abstract":"本书作者威廉·欧奈尔是华尔街经验最丰富、最成功的资深投资人之一，他21岁白手起家，30岁就买下纽约证券交易所的席次。他创办的《投资者商业日报》是《华尔街日报... ","buylinks":"https://book.douban.com/subject/4244804/buylinks","price":"\n        纸质版 52.20元\n      "},{"src":"https://img2.doubanio.com/view/subject/s/public/s1234142.jpg","href":"https://book.douban.com/subject/1058131/","title":"金融炼金术","subtitle":"","rating":"8.4","pub":"\n        \n  \n  [美] 乔治·索罗斯 / 孙忠/等 / 海南出版社 / 1999-4 / 24.80元\n\n      ","pl":"\n        (2647人评价)\n    ","abstract":"本书是索罗斯的投资日记。读者可以从中欣赏到索罗斯如何分析个股、如何把握市场转变的时机、如何面对不利的市场行情并及时调整对策，从而在风云变幻的金融市场中立于不... ","buylinks":"https://book.douban.com/subject/1058131/buylinks","price":"\n        纸质版 17.10元\n      "},{"src":"https://img1.doubanio.com/view/subject/s/public/s29611639.jpg","href":"https://book.douban.com/subject/1007459/","title":"怎样选择成长股","subtitle":"","rating":"8.5","pub":"\n        \n  \n  菲利普.A.费舍 / 罗耀宗 / 海南出版社 / 1999-10 / 19.80\n\n      ","pl":"\n        (1479人评价)\n    ","abstract":"作者希望这种书能以非正式的写法，把他想讲的事情以第一人称的方式，告诉身为读者的大家。书内用到的大部分语言、许多例子和比喻，和作者把这些观念亲口告诉买他基金的... ","buylinks":"https://book.douban.com/subject/1007459/buylinks","price":"\n        纸质版 32.10元起\n      "},{"src":"https://img3.doubanio.com/view/subject/s/public/s6255930.jpg","href":"https://book.douban.com/subject/5382213/","title":"股票大作手回忆录","subtitle":"","rating":"8.8","pub":"\n        \n  \n  埃德温·勒菲弗 / 丁圣元 / 万卷出版公司出版 / 2010-11 / 48.00元\n\n      ","pl":"\n        (2546人评价)\n    ","abstract":"《股票大作手回忆录》是一本精彩的人物传记，记述了一位几百年一遇的金融市场交易与投资天才——杰西·利弗莫尔（Jesse Lauriston Livermore... ","buylinks":"https://book.douban.com/subject/5382213/buylinks","price":"\n        纸质版 35.20元\n      "},{"src":"https://img1.doubanio.com/view/subject/s/public/s33634567.jpg","href":"https://book.douban.com/subject/27088971/","title":"财务报表分析与股票估值","subtitle":"","rating":"8.8","pub":"\n        \n  \n  郭永清 / 机械工业出版社 / 2017-7 / 69.00元\n\n      ","pl":"\n        (380人评价)\n    ","abstract":"本书作者郭永清是上海国家会计学院著名财务学教授。本书是郭永清教授多年来讲授财报分析以及自己进行股票投资实践的总结。\n本书的财报分析内容曾在上海国家会计学院多... ","buylinks":"https://book.douban.com/subject/27088971/buylinks","price":"\n        纸质版 61.70元\n      "},{"src":"https://img1.doubanio.com/view/subject/s/public/s24969678.jpg","href":"https://book.douban.com/subject/1182173/","title":"炒股的智慧","subtitle":" : 在华尔街炒股为生的体验(修订版) ","rating":"8.9","pub":"\n        \n  \n  陈江挺 / 经济科学出版社 / 2004-1 / 22.00元\n\n      ","pl":"\n        (2686人评价)\n    ","abstract":"作者以在华尔街十多年投资股市的经验教训为感性素材，在研读了西方几百年来的炒股名著和炒股大师传记的基础之上，对投资股市最根本、最重要的问题进行了深入的思考和探... ","buylinks":"https://book.douban.com/subject/1182173/buylinks","price":"\n        纸质版 19.40元\n      "},{"src":"https://img2.doubanio.com/view/subject/s/public/s6097983.jpg","href":"https://book.douban.com/subject/4137173/","title":"股市真规则","subtitle":"","rating":"9.0","pub":"\n        \n  \n  [美] 帕特·多尔西 / 司福连、刘静 / 中信出版社 / 2010-1 / 39.00元\n\n      ","pl":"\n        (1110人评价)\n    ","abstract":"《股市真规则(第2版)》：如果只用一本经典指导自己的股票投资，那就是最好的选择！站在巴菲特和晨星公司的肩膀上投资。\n这《股市真规则(第2版)》主要讲述了公司... ","buylinks":"https://book.douban.com/subject/4137173/buylinks","price":"\n        纸质版 29.30元\n      "},{"src":"https://img1.doubanio.com/view/subject/s/public/s2650509.jpg","href":"https://book.douban.com/subject/2189613/","title":"战胜华尔街","subtitle":"","rating":"8.4","pub":"\n        \n  \n  [美]彼得·林奇、约翰·罗瑟查尔德 / 机械工业出版社 / 2007-8-1 / 48.00元\n\n      ","pl":"\n        (2350人评价)\n    ","abstract":"彼得•林奇，全球最佳选股者、美国证券界超级巨星、历史上最传奇的基金经理人\n继《彼得•林奇的成功投资》之后，《战胜华尔街》是林奇专门为业余投资者写的一本林奇股... ","buylinks":"https://book.douban.com/subject/2189613/buylinks","price":"\n        纸质版 43.20元\n      "}]