[{"src":"https://img9.doubanio.com/view/subject/s/public/s26720726.jpg","href":"https://book.douban.com/subject/24754316/","title":"最好的我们","subtitle":"","rating":"8.7","pub":"\n        \n  \n  八月长安 / 湖南文艺出版社 / 2013-8-5 / 55\n\n      ","pl":"\n        (58097人评价)\n    ","abstract":"你总是说青春从不曾永远，而那时候的我们，就是最好的我们。\n这一次，我们和整个青春做告别。\n八月长安全新力作。\n你还记得高中时的同桌吗？那个少年有世界上最明朗... ","buylinks":"https://book.douban.com/subject/24754316/buylinks","price":"\n        纸质版 37.80元\n      "},{"src":"https://img3.doubanio.com/view/subject/s/public/s4130990.jpg","href":"https://book.douban.com/subject/4231381/","title":"那些回不去的年少时光","subtitle":"","rating":"8.4","pub":"\n        \n  \n  桐华 / 江苏文艺出版社 / 2010-01 / 23.80元\n\n      ","pl":"\n        (49838人评价)\n    ","abstract":"最值得珍藏的怀旧读物，写给年少自己的书，纪念我们共同的青春和成长\n您还记得上世纪最后十年的青春是怎样吗？那可是我们独一无二的成长！\n那些回不去的年少时光》以... ","buylinks":"https://book.douban.com/subject/4231381/buylinks","price":"\n        纸质版 23.80元\n      "},{"src":"https://img3.doubanio.com/view/subject/s/public/s29923410.jpg","href":"https://book.douban.com/subject/26858577/","title":"少年的你，如此美丽","subtitle":"","rating":"6.1","pub":"\n        \n  \n  玖月晞 / 百花洲文艺出版社 / 2016-9 / 32.00元\n\n      ","pl":"\n        (11445人评价)\n    ","abstract":"你有没有为一个人，拼了命地去努力过？\n\n北望今心，陈年不移。\n曾经，是谁在夏天的灿烂阳光下拿树枝写下一个名字，告知少年，今心；\n曾经，是谁用目光引诱她念诵一... ","buylinks":"https://book.douban.com/subject/26858577/buylinks","price":"\n        纸质版 19.10元\n      "},{"src":"https://img9.doubanio.com/view/subject/s/public/s1320494.jpg","href":"https://book.douban.com/subject/1291760/","title":"会有天使替我爱你","subtitle":"","rating":"6.6","pub":"\n        \n  \n  明晓溪 / 新世界出版社 / 2005-5 / 20.00元\n\n      ","pl":"\n        (48605人评价)\n    ","abstract":"《会有天使替我爱你》是一部校园爱情小说，先在网络连载。\n小米因为死去男友的心脏移植给了另外一个男孩而转学来到了他所在的学校，这个男孩——尹堂曜同明晓溪所有小... ","buylinks":"https://book.douban.com/subject/1291760/buylinks","price":"\n        纸质版 10.40元\n      "},{"src":"https://img9.doubanio.com/view/subject/s/public/s28357474.jpg","href":"https://book.douban.com/subject/26680113/","title":"那个不为人知的故事","subtitle":"","rating":"8.6","pub":"\n        \n  \n  twentine / 江苏文艺出版社 / 2015-12 / 32.00元\n\n      ","pl":"\n        (14310人评价)\n    ","abstract":"我曾拥有一段时光\n在那段时光里\n我能用我贫瘠的词语描绘出每一分每一秒\n我能用我枯竭的心灵记住所有的细节\n但这段时光很短暂\n就像一个故事刚刚有了开篇就戛然而止... ","buylinks":"https://book.douban.com/subject/26680113/buylinks","price":"\n        纸质版 36.20元起\n      "},{"src":"https://img9.doubanio.com/view/subject/s/public/s27220774.jpg","href":"https://book.douban.com/subject/25829434/","title":"暗恋·橘生淮南","subtitle":"","rating":"7.9","pub":"\n        \n  \n  八月长安 / 湖南文艺出版社 / 2014-7-25 / 58\n\n      ","pl":"\n        (16981人评价)\n    ","abstract":"所有的等待都是值得的。八月长安“振华三部曲”典藏收官，四十万字全新修订，五万字全新内容，套装全两册。\n2008年到现在，时光或许改变了一切，但一个创作者的初... ","buylinks":"https://book.douban.com/subject/25829434/buylinks","price":"\n        纸质版 57.40元\n      "},{"src":"https://img1.doubanio.com/view/subject/s/public/s29543659.jpg","href":"https://book.douban.com/subject/27139846/","title":"我在未来等你","subtitle":"","rating":"7.1","pub":"\n        \n  \n  刘同 / 北京联合出版公司 / 2017-9 / 42.00\n\n      ","pl":"\n        (5052人评价)\n    ","abstract":"你会不会偶尔产生那种“如果能回到那一年就好了”的念头？觉得回到那一年，以我们当下的见识和心态，很多事都能被改变。\n---------------------... ","buylinks":"https://book.douban.com/subject/27139846/buylinks","price":"\n        纸质版 28.20元\n      "},{"src":"https://img9.doubanio.com/view/subject/s/public/s29357154.jpg","href":"https://book.douban.com/subject/26978506/","title":"打火机与公主裙·荒草园","subtitle":"","rating":"8.3","pub":"\n        \n  \n  Twentine / 青岛出版社 / 2017-3 / 36.00元\n\n      ","pl":"\n        (8038人评价)\n    ","abstract":"“如果人临死前真有走马灯这个环节，她大概会是我这辈子见的最后一人。”\n从青涩的校园时代里一抹明亮的金，到厮杀的职场中那化不开的黑，李峋就像荒芜之地的一株野草... ","price":"","buyhref":"https://book.douban.com/subject/26978506/?channel=subject_list&platform=web"},{"src":"https://img9.doubanio.com/view/subject/s/public/s2405994.jpg","href":"https://book.douban.com/subject/2062200/","title":"悲伤逆流成河","subtitle":"","rating":"6.2","pub":"\n        \n  \n  郭敬明 / 长江文艺出版社 / 2007-5 / 24.00元\n\n      ","pl":"\n        (101443人评价)\n    ","abstract":"你曾经有梦见这样无边无际的月光下的水域么？\n无声起伏的黑色的巨浪，在地平线上爆发出沉默的力量。\n就这样，从仅仅打湿脚底，到盖住脚背，漫过小腿，一步一步地，走... ","buylinks":"https://book.douban.com/subject/2062200/buylinks","price":"\n        纸质版 12.50元\n      "},{"src":"https://img9.doubanio.com/view/subject/s/public/s3251696.jpg","href":"https://book.douban.com/subject/3191328/","title":"小时代1.0折纸时代","subtitle":"","rating":"6.5","pub":"\n        \n  \n  郭敬明 / 长江文艺出版社 / 2008-10 / 29.80元\n\n      ","pl":"\n        (70406人评价)\n    ","abstract":"故事以经济飞速发展的上海这座风光而时尚的城市为背景，讲述了林萧、南湘、顾里、唐宛如四个从小感情深厚、有着不同价值观和人生观的女生，先后所经历的友情、爱情，乃... ","buylinks":"https://book.douban.com/subject/3191328/buylinks","price":"\n        纸质版 29.80元\n      "},{"src":"https://img9.doubanio.com/view/subject/s/public/s4296814.jpg","href":"https://book.douban.com/subject/4732378/","title":"那些回不去的年少时光·终场","subtitle":"","rating":"8.7","pub":"\n        \n  \n  桐华 / 江苏文艺出版社 / 2010-04 / 23.80元\n\n      ","pl":"\n        (20053人评价)\n    ","abstract":"故事虽落幕，青春不终场！经过孤独的小学时光，混乱的初中生涯，罗琦琦来到了高中。和所有走过那段岁月的人一样，面对高考的折磨，罗琦琦虽然不情愿，却也无法做到不在... ","buylinks":"https://book.douban.com/subject/4732378/buylinks","price":"\n        纸质版 23.80元\n      "},{"src":"https://img9.doubanio.com/view/subject/s/public/s4345304.jpg","href":"https://book.douban.com/subject/4818929/","title":"夏至未至","subtitle":"","rating":"7.6","pub":"\n        \n  \n  郭敬明 / 长江文艺出版社 / 2010-4 / 26.80元\n\n      ","pl":"\n        (19775人评价)\n    ","abstract":"故事开始于一个虚构的城市浅川，一个深北方长满高大香樟的城市。几个年轻的人开始自己的高中生活，一切都似乎格外的平静和缓慢，带着夏日特有的让人昏昏欲睡的叙述情绪... ","buylinks":"https://book.douban.com/subject/4818929/buylinks","price":"\n        纸质版 3.80元起\n      "},{"src":"https://img9.doubanio.com/view/subject/s/public/s24476315.jpg","href":"https://book.douban.com/subject/20278327/","title":"谁的青春不迷茫","subtitle":" : 一个奋斗小青年的逆袭人生 ","rating":"5.8","pub":"\n        \n  \n  刘同 / 中信出版社 / 2012-12 / 35.00元\n\n      ","pl":"\n        (19127人评价)\n    ","abstract":"奋斗小青年刘同 十年逆袭人生\n给都市中焦躁不安困惑迷茫的年轻人\n一个人，十年光阴；一座城，瞬息万变\n如果做不到让你深省思考，那就努力让你会心一笑\n150万字... ","buylinks":"https://book.douban.com/subject/20278327/buylinks","price":"\n        纸质版 17.50元\n      "},{"src":"https://img9.doubanio.com/view/subject/s/public/s33670056.jpg","href":"https://book.douban.com/subject/35088369/","title":"了不起的郝大小","subtitle":"","rating":"9.1","pub":"\n        \n  \n  周婉京 / 团结出版社 / 2020-8 / 39.8\n\n      ","pl":"\n        (52人评价)\n    ","abstract":"《了不起的郝大小》是周婉京女性主义小说的最新一部，也是她的“了不起”系列的第一部。讲述了两个女主人公郝大小与袁小馍从19岁到20岁的生活变化。故事随着袁小馍... ","buylinks":"https://book.douban.com/subject/35088369/buylinks","price":"\n        纸质版 34.30元\n      "},{"src":"https://img2.doubanio.com/view/subject/s/public/s7011412.jpg","href":"https://book.douban.com/subject/6828611/","title":"小时代3.0：刺金时代","subtitle":"","rating":"6.2","pub":"\n        \n  \n  郭敬明 / 长江文艺出版社 / 2011-12 / 32.80元\n\n      ","pl":"\n        (21230人评价)\n    ","abstract":"“小时代”系列的完结篇《小时代3.0 刺金时代》，将要为林萧、顾里、南湘、唐宛如四位主角，以及简溪、顾源、宫洺、周崇光、Neil……他们所有人的故事，画上出... ","buylinks":"https://book.douban.com/subject/6828611/buylinks","price":"\n        纸质版 32.50元\n      "},{"src":"https://img1.doubanio.com/view/subject/s/public/s6531687.jpg","href":"https://book.douban.com/subject/5686369/","title":"何以笙箫默","subtitle":"","rating":"7.7","pub":"\n        \n  \n  顾漫 / 沈阳出版社 / 2011-1 / 25.00元\n\n      ","pl":"\n        (19615人评价)\n    ","abstract":"我还记得与他们初遇在人群熙攘的超市，就像在后记里写的那样，忽然就冒出那样一种感触攫住了我。也许早一步，晚一步，他们不是他们，我不是我，谁知道呢，缘分总是那么... ","buylinks":"https://book.douban.com/subject/5686369/buylinks","price":"\n        纸质版 20.00元\n      "},{"src":"https://img9.doubanio.com/view/subject/s/public/s1520215.jpg","href":"https://book.douban.com/subject/1469051/","title":"左耳","subtitle":"","rating":"6.9","pub":"\n        \n  \n  饶雪漫 / 当代世界出版社 / 2006-2 / 22.00元\n\n      ","pl":"\n        (43416人评价)\n    ","abstract":"该书延续了作者一贯的创作路线，讲述关于青春成长的故事。但经过多年的写作实践后，饶雪漫创作的喷发期终于到来，《左耳》被各界一致认为是饶雪漫的巅峰之作。它生动地... ","buylinks":"https://book.douban.com/subject/1469051/buylinks","price":"\n        纸质版 7.50元起\n      "},{"src":"https://img9.doubanio.com/view/subject/s/public/s1789356.jpg","href":"https://book.douban.com/subject/1855343/","title":"泡沫之夏Ⅱ","subtitle":"","rating":"7.0","pub":"\n        \n  \n  明晓溪 / 新世界出版社 / 2006-8 / 22.00元\n\n      ","pl":"\n        (23254人评价)\n    ","abstract":"夏沫投身演艺圈，再次走进欧辰的生命，洛熙成了夏沫的男友，当失忆的少爷慢慢回想起曾经的缠绵，当耀眼的洛熙突然失去了巨星的光芒，5年后的夏沫该何去何从？三个人的... ","buylinks":"https://book.douban.com/subject/1855343/buylinks","price":"\n        纸质版 23.80元\n      "},{"src":"https://img9.doubanio.com/view/subject/s/public/s3658646.jpg","href":"https://book.douban.com/subject/3598313/","title":"西决","subtitle":"","rating":"7.9","pub":"\n        \n  \n  笛安 / 长江文艺出版社 / 2009-3 / 22.80元\n\n      ","pl":"\n        (56240人评价)\n    ","abstract":"仇恨，是种类似于某些中药材的东西，性寒、微苦，沉淀在人体中，散发着植物的清香。可是天长日久，却总是能催生一场又一场血肉横飞的爆炸。核武器、手榴弹、炸药包，当... ","buylinks":"https://book.douban.com/subject/3598313/buylinks","price":"\n        纸质版 22.80元\n      "},{"src":"https://img2.doubanio.com/view/subject/s/public/s3251672.jpg","href":"https://book.douban.com/subject/3194071/","title":"少年巴比伦","subtitle":"","rating":"8.6","pub":"\n        \n  \n  路内 / 重庆出版社 / 2008-8 / 22.00元\n\n      ","pl":"\n        (8649人评价)\n    ","abstract":"上个世纪90年代的戴城，路小路在一家化工厂上班，他是个愣头青，不知道未来和生活目标在哪里。跟着一个叫“老牛逼”的师傅混，没学会半点技术。在机修班，除了拧螺丝... ","buylinks":"https://book.douban.com/subject/3194071/buylinks","price":"\n        纸质版 27.30元起\n      "}]